<xml version="1.0">
<dashboard>
	<widget field="Pitch" type="Number" class="edu.wpi.first.smartdashboard.gui.elements.TextBox">
		<location x="0" y="151"/>
	</widget>
	<widget field="Gyro2" type="Number" class="edu.wpi.first.smartdashboard.gui.elements.TextBox">
		<location x="0" y="130"/>
	</widget>
	<widget field="Roll" type="Number" class="edu.wpi.first.smartdashboard.gui.elements.TextBox">
		<location x="0" y="109"/>
	</widget>
	<widget field="Yaw" type="Number" class="edu.wpi.first.smartdashboard.gui.elements.TextBox">
		<location x="0" y="88"/>
	</widget>
	<widget field="Gyro" type="Number" class="edu.wpi.first.smartdashboard.gui.elements.TextBox">
		<location x="0" y="67"/>
	</widget>
	<widget field="Auto choices" type="String Chooser" class="edu.wpi.first.smartdashboard.gui.elements.Chooser">
		<location x="0" y="0"/>
	</widget>
	<widget field="Drivetrain" type="Subsystem" class="edu.wpi.first.smartdashboard.gui.elements.Subsystem">
		<location x="0" y="173"/>
	</widget>
</dashboard>
<live-window>
</live-window>
</xml>